{
  "version": 1,
  "updatedAt": "2026-06-27T05:22:19.994Z",
  "family": "cooperation",
  "shard": 140,
  "shardCount": 147,
  "evidence": [
    {
      "term": "问号",
      "evidenceSamples": [
        "为毛大家都在发问号，这个掉头没问题的= =搞笑的在后面",
        "2077也是满地图问号",
        "2077满地图问号",
        "巫师3的有的问号是一段支线或者一段故事，很精彩",
        "把问号去了就是很神经[笑哭]感觉莫名其妙的"
      ],
      "evidenceSources": [
        {
          "source": "Bilibili public search-discovered video comment scan: https://www.bilibili.com/video/BV1gM4m1C7Bz/, https://www.bilibili.com/video/BV1gVj46TEdW/, https://www.bilibili.com/video/BV13GE86HEP1/, https://www.bilibili.com/video/BV1aERYBDEfW/, https://www.bilibili.com/video/BV1zZ7a6vEKn/, https://www.bilibili.com/video/BV1AS7e6UEMZ/, http://www.bilibili.com/video/av1304481691, http://www.bilibili.com/video/av116514426456638, http://www.bilibili.com/video/av116097781079423, http://www.bilibili.com/video/av115428118567508, http://www.bilibili.com/video/av116377188899374, http://www.bilibili.com/video/av114297199921566, http://www.bilibili.com/video/av115914506901381, http://www.bilibili.com/video/av116454011704329, http://www.bilibili.com/video/av115967875095293, http://www.bilibili.com/video/av1301037679, http://www.bilibili.com/video/av485893597, http://www.bilibili.com/video/av113648475374138, http://www.bilibili.com/video/av113114322306258, http://www.bilibili.com/video/av113291875583522, http://www.bilibili.com/video/av904253717, http://www.bilibili.com/video/av114359946708511, http://www.bilibili.com/video/av113587607570846, http://www.bilibili.com/video/av115252964362911, http://www.bilibili.com/video/av114034519056120, http://www.bilibili.com/video/av114409724777935, http://www.bilibili.com/video/av116640658229084, http://www.bilibili.com/video/av116786250981048, http://www.bilibili.com/video/av116810913550691, http://www.bilibili.com/video/av116759524804472, http://www.bilibili.com/video/av116805276274015, http://www.bilibili.com/video/av116810242333394, http://www.bilibili.com/video/av114841872240003, http://www.bilibili.com/video/av116809168655429, http://www.bilibili.com/video/av116811567728119, http://www.bilibili.com/video/av116808732379349, http://www.bilibili.com/video/av116810795977376, http://www.bilibili.com/video/av787111910, http://www.bilibili.com/video/av116809185559372, http://www.bilibili.com/video/av116688691399347, http://www.bilibili.com/video/av116808094915256, http://www.bilibili.com/video/av116710233345555",
          "uid": "BV1gM4m1C7Bz,BV1gVj46TEdW,BV13GE86HEP1,BV1aERYBDEfW,BV1zZ7a6vEKn,BV1AS7e6UEMZ",
          "sample": "为毛大家都在发问号，这个掉头没问题的= =搞笑的在后面"
        },
        {
          "source": "Bilibili public search-discovered video comment scan: https://www.bilibili.com/video/BV1Bp4y1L7Mi/, https://www.bilibili.com/video/BV13wjn6nEMX/, https://www.bilibili.com/video/BV17n7F66Eec/, https://www.bilibili.com/video/BV1eL411k73U/, https://www.bilibili.com/video/BV1RN7g6hEWr/, https://www.bilibili.com/video/BV1y67u6mEVR/, https://www.bilibili.com/video/BV1c5411H7Qm/, https://www.bilibili.com/video/BV12rjU64Ejg/, https://www.bilibili.com/video/BV1o2jJ6hEfs/, https://www.bilibili.com/video/BV1c7EJ6MErH/, http://www.bilibili.com/video/av958210020, http://www.bilibili.com/video/av441011570, http://www.bilibili.com/video/av458711317, http://www.bilibili.com/video/av116703858004130, http://www.bilibili.com/video/av492844033, http://www.bilibili.com/video/av1354287633, http://www.bilibili.com/video/av749441259, http://www.bilibili.com/video/av316020504, http://www.bilibili.com/video/av606346540, http://www.bilibili.com/video/av116364840797386, http://www.bilibili.com/video/av999538829, http://www.bilibili.com/video/av651724016, http://www.bilibili.com/video/av115919070167290, http://www.bilibili.com/video/av759576650, http://www.bilibili.com/video/av112822281374491, http://www.bilibili.com/video/av116618579411550, http://www.bilibili.com/video/av114069382171622, http://www.bilibili.com/video/av116052180606708, http://www.bilibili.com/video/av116469379630813, http://www.bilibili.com/video/av116409870846638, http://www.bilibili.com/video/av116409686300459, http://www.bilibili.com/video/av115076266856479, http://www.bilibili.com/video/av115202146308259, http://www.bilibili.com/video/av115807854003391, http://www.bilibili.com/video/av114766794262550, http://www.bilibili.com/video/av113073251681541, http://www.bilibili.com/video/av116118349946532, http://www.bilibili.com/video/av113538265979830, http://www.bilibili.com/video/av116068689383734, http://www.bilibili.com/video/av115516802864145, http://www.bilibili.com/video/av113980026656610, http://www.bilibili.com/video/av114011735592522, http://www.bilibili.com/video/av113271642327481, http://www.bilibili.com/video/av113259696883749, http://www.bilibili.com/video/av116158665727966, http://www.bilibili.com/video/av447741936, http://www.bilibili.com/video/av116047097110398, http://www.bilibili.com/video/av113855539845800, http://www.bilibili.com/video/av116781654022932, http://www.bilibili.com/video/av116797089059081, http://www.bilibili.com/video/av116799806964149, http://www.bilibili.com/video/av116797239992173, http://www.bilibili.com/video/av116796082356670, http://www.bilibili.com/video/av116788801180707, http://www.bilibili.com/video/av116791653243680, http://www.bilibili.com/video/av114182829643950, http://www.bilibili.com/video/av116793096085171, http://www.bilibili.com/video/av116799169369825, http://www.bilibili.com/video/av116798582228750, http://www.bilibili.com/video/av116790277442885, http://www.bilibili.com/video/av116792357881965, http://www.bilibili.com/video/av116796887732372, http://www.bilibili.com/video/av116799622352185, http://www.bilibili.com/video/av116799286811585, http://www.bilibili.com/video/av116798800266624, http://www.bilibili.com/video/av116793834216360, http://www.bilibili.com/video/av116798397612326, http://www.bilibili.com/video/av116781117084793, http://www.bilibili.com/video/av116798045293134, http://www.bilibili.com/video/av116797323941441, http://www.bilibili.com/video/av116790025853625, http://www.bilibili.com/video/av116783130351160, http://www.bilibili.com/video/av116658827957471, http://www.bilibili.com/video/av116781620595269, http://www.bilibili.com/video/av116686829130049, http://www.bilibili.com/video/av114907890586372, http://www.bilibili.com/video/av116796669561469, http://www.bilibili.com/video/av112924672788549, http://www.bilibili.com/video/av114254434798357, http://www.bilibili.com/video/av116753115911683, http://www.bilibili.com/video/av116797357498025, http://www.bilibili.com/video/av116713152579547, http://www.bilibili.com/video/av116790663319852, http://www.bilibili.com/video/av116795209944552, http://www.bilibili.com/video/av116566033174320, http://www.bilibili.com/video/av116778483064805, http://www.bilibili.com/video/av935428079, http://www.bilibili.com/video/av116771151419984, http://www.bilibili.com/video/av1601962814, http://www.bilibili.com/video/av116760984422954, http://www.bilibili.com/video/av116793783946781",
          "uid": "BV1Bp4y1L7Mi,BV13wjn6nEMX,BV17n7F66Eec,BV1eL411k73U,BV1RN7g6hEWr,BV1y67u6mEVR,BV1c5411H7Qm,BV12rjU64Ejg,BV1o2jJ6hEfs,BV1c7EJ6MErH",
          "sample": "2077也是满地图问号"
        },
        {
          "source": "Bilibili public search-discovered video comment scan: https://www.bilibili.com/video/BV1Bp4y1L7Mi/, https://www.bilibili.com/video/BV13wjn6nEMX/, https://www.bilibili.com/video/BV17n7F66Eec/, https://www.bilibili.com/video/BV1eL411k73U/, https://www.bilibili.com/video/BV1RN7g6hEWr/, https://www.bilibili.com/video/BV1y67u6mEVR/, https://www.bilibili.com/video/BV1c5411H7Qm/, https://www.bilibili.com/video/BV12rjU64Ejg/, https://www.bilibili.com/video/BV1o2jJ6hEfs/, https://www.bilibili.com/video/BV1c7EJ6MErH/, http://www.bilibili.com/video/av958210020, http://www.bilibili.com/video/av441011570, http://www.bilibili.com/video/av458711317, http://www.bilibili.com/video/av116703858004130, http://www.bilibili.com/video/av492844033, http://www.bilibili.com/video/av1354287633, http://www.bilibili.com/video/av749441259, http://www.bilibili.com/video/av316020504, http://www.bilibili.com/video/av606346540, http://www.bilibili.com/video/av116364840797386, http://www.bilibili.com/video/av999538829, http://www.bilibili.com/video/av651724016, http://www.bilibili.com/video/av115919070167290, http://www.bilibili.com/video/av759576650, http://www.bilibili.com/video/av112822281374491, http://www.bilibili.com/video/av116618579411550, http://www.bilibili.com/video/av114069382171622, http://www.bilibili.com/video/av116052180606708, http://www.bilibili.com/video/av116469379630813, http://www.bilibili.com/video/av116409870846638, http://www.bilibili.com/video/av116409686300459, http://www.bilibili.com/video/av115076266856479, http://www.bilibili.com/video/av115202146308259, http://www.bilibili.com/video/av115807854003391, http://www.bilibili.com/video/av114766794262550, http://www.bilibili.com/video/av113073251681541, http://www.bilibili.com/video/av116118349946532, http://www.bilibili.com/video/av113538265979830, http://www.bilibili.com/video/av116068689383734, http://www.bilibili.com/video/av115516802864145, http://www.bilibili.com/video/av113980026656610, http://www.bilibili.com/video/av114011735592522, http://www.bilibili.com/video/av113271642327481, http://www.bilibili.com/video/av113259696883749, http://www.bilibili.com/video/av116158665727966, http://www.bilibili.com/video/av447741936, http://www.bilibili.com/video/av116047097110398, http://www.bilibili.com/video/av113855539845800, http://www.bilibili.com/video/av116781654022932, http://www.bilibili.com/video/av116797089059081, http://www.bilibili.com/video/av116799806964149, http://www.bilibili.com/video/av116797239992173, http://www.bilibili.com/video/av116796082356670, http://www.bilibili.com/video/av116788801180707, http://www.bilibili.com/video/av116791653243680, http://www.bilibili.com/video/av114182829643950, http://www.bilibili.com/video/av116793096085171, http://www.bilibili.com/video/av116799169369825, http://www.bilibili.com/video/av116798582228750, http://www.bilibili.com/video/av116790277442885, http://www.bilibili.com/video/av116792357881965, http://www.bilibili.com/video/av116796887732372, http://www.bilibili.com/video/av116799622352185, http://www.bilibili.com/video/av116799286811585, http://www.bilibili.com/video/av116798800266624, http://www.bilibili.com/video/av116793834216360, http://www.bilibili.com/video/av116798397612326, http://www.bilibili.com/video/av116781117084793, http://www.bilibili.com/video/av116798045293134, http://www.bilibili.com/video/av116797323941441, http://www.bilibili.com/video/av116790025853625, http://www.bilibili.com/video/av116783130351160, http://www.bilibili.com/video/av116658827957471, http://www.bilibili.com/video/av116781620595269, http://www.bilibili.com/video/av116686829130049, http://www.bilibili.com/video/av114907890586372, http://www.bilibili.com/video/av116796669561469, http://www.bilibili.com/video/av112924672788549, http://www.bilibili.com/video/av114254434798357, http://www.bilibili.com/video/av116753115911683, http://www.bilibili.com/video/av116797357498025, http://www.bilibili.com/video/av116713152579547, http://www.bilibili.com/video/av116790663319852, http://www.bilibili.com/video/av116795209944552, http://www.bilibili.com/video/av116566033174320, http://www.bilibili.com/video/av116778483064805, http://www.bilibili.com/video/av935428079, http://www.bilibili.com/video/av116771151419984, http://www.bilibili.com/video/av1601962814, http://www.bilibili.com/video/av116760984422954, http://www.bilibili.com/video/av116793783946781",
          "uid": "BV1Bp4y1L7Mi,BV13wjn6nEMX,BV17n7F66Eec,BV1eL411k73U,BV1RN7g6hEWr,BV1y67u6mEVR,BV1c5411H7Qm,BV12rjU64Ejg,BV1o2jJ6hEfs,BV1c7EJ6MErH",
          "sample": "2077满地图问号"
        },
        {
          "source": "Bilibili public search-discovered video comment scan: https://www.bilibili.com/video/BV1Bp4y1L7Mi/, https://www.bilibili.com/video/BV13wjn6nEMX/, https://www.bilibili.com/video/BV17n7F66Eec/, https://www.bilibili.com/video/BV1eL411k73U/, https://www.bilibili.com/video/BV1RN7g6hEWr/, https://www.bilibili.com/video/BV1y67u6mEVR/, https://www.bilibili.com/video/BV1c5411H7Qm/, https://www.bilibili.com/video/BV12rjU64Ejg/, https://www.bilibili.com/video/BV1o2jJ6hEfs/, https://www.bilibili.com/video/BV1c7EJ6MErH/, http://www.bilibili.com/video/av958210020, http://www.bilibili.com/video/av441011570, http://www.bilibili.com/video/av458711317, http://www.bilibili.com/video/av116703858004130, http://www.bilibili.com/video/av492844033, http://www.bilibili.com/video/av1354287633, http://www.bilibili.com/video/av749441259, http://www.bilibili.com/video/av316020504, http://www.bilibili.com/video/av606346540, http://www.bilibili.com/video/av116364840797386, http://www.bilibili.com/video/av999538829, http://www.bilibili.com/video/av651724016, http://www.bilibili.com/video/av115919070167290, http://www.bilibili.com/video/av759576650, http://www.bilibili.com/video/av112822281374491, http://www.bilibili.com/video/av116618579411550, http://www.bilibili.com/video/av114069382171622, http://www.bilibili.com/video/av116052180606708, http://www.bilibili.com/video/av116469379630813, http://www.bilibili.com/video/av116409870846638, http://www.bilibili.com/video/av116409686300459, http://www.bilibili.com/video/av115076266856479, http://www.bilibili.com/video/av115202146308259, http://www.bilibili.com/video/av115807854003391, http://www.bilibili.com/video/av114766794262550, http://www.bilibili.com/video/av113073251681541, http://www.bilibili.com/video/av116118349946532, http://www.bilibili.com/video/av113538265979830, http://www.bilibili.com/video/av116068689383734, http://www.bilibili.com/video/av115516802864145, http://www.bilibili.com/video/av113980026656610, http://www.bilibili.com/video/av114011735592522, http://www.bilibili.com/video/av113271642327481, http://www.bilibili.com/video/av113259696883749, http://www.bilibili.com/video/av116158665727966, http://www.bilibili.com/video/av447741936, http://www.bilibili.com/video/av116047097110398, http://www.bilibili.com/video/av113855539845800, http://www.bilibili.com/video/av116781654022932, http://www.bilibili.com/video/av116797089059081, http://www.bilibili.com/video/av116799806964149, http://www.bilibili.com/video/av116797239992173, http://www.bilibili.com/video/av116796082356670, http://www.bilibili.com/video/av116788801180707, http://www.bilibili.com/video/av116791653243680, http://www.bilibili.com/video/av114182829643950, http://www.bilibili.com/video/av116793096085171, http://www.bilibili.com/video/av116799169369825, http://www.bilibili.com/video/av116798582228750, http://www.bilibili.com/video/av116790277442885, http://www.bilibili.com/video/av116792357881965, http://www.bilibili.com/video/av116796887732372, http://www.bilibili.com/video/av116799622352185, http://www.bilibili.com/video/av116799286811585, http://www.bilibili.com/video/av116798800266624, http://www.bilibili.com/video/av116793834216360, http://www.bilibili.com/video/av116798397612326, http://www.bilibili.com/video/av116781117084793, http://www.bilibili.com/video/av116798045293134, http://www.bilibili.com/video/av116797323941441, http://www.bilibili.com/video/av116790025853625, http://www.bilibili.com/video/av116783130351160, http://www.bilibili.com/video/av116658827957471, http://www.bilibili.com/video/av116781620595269, http://www.bilibili.com/video/av116686829130049, http://www.bilibili.com/video/av114907890586372, http://www.bilibili.com/video/av116796669561469, http://www.bilibili.com/video/av112924672788549, http://www.bilibili.com/video/av114254434798357, http://www.bilibili.com/video/av116753115911683, http://www.bilibili.com/video/av116797357498025, http://www.bilibili.com/video/av116713152579547, http://www.bilibili.com/video/av116790663319852, http://www.bilibili.com/video/av116795209944552, http://www.bilibili.com/video/av116566033174320, http://www.bilibili.com/video/av116778483064805, http://www.bilibili.com/video/av935428079, http://www.bilibili.com/video/av116771151419984, http://www.bilibili.com/video/av1601962814, http://www.bilibili.com/video/av116760984422954, http://www.bilibili.com/video/av116793783946781",
          "uid": "BV1Bp4y1L7Mi,BV13wjn6nEMX,BV17n7F66Eec,BV1eL411k73U,BV1RN7g6hEWr,BV1y67u6mEVR,BV1c5411H7Qm,BV12rjU64Ejg,BV1o2jJ6hEfs,BV1c7EJ6MErH",
          "sample": "巫师3的有的问号是一段支线或者一段故事，很精彩"
        },
        {
          "source": "Bilibili public search-discovered video comment scan: https://www.bilibili.com/video/BV1wi421R7cx/, https://www.bilibili.com/video/BV1uB4y1H7n3/, https://www.bilibili.com/video/BV1j1NUeNEx6/, https://www.bilibili.com/video/BV1WqLm67E2r/, http://www.bilibili.com/video/av1452249192, http://www.bilibili.com/video/av603171348, http://www.bilibili.com/video/av113973684867426, http://www.bilibili.com/video/av116606919318437",
          "uid": "BV1wi421R7cx,BV1uB4y1H7n3,BV1j1NUeNEx6,BV1WqLm67E2r",
          "sample": "把问号去了就是很神经[笑哭]感觉莫名其妙的"
        },
        {
          "source": "Bilibili public search-discovered video comment scan: https://www.bilibili.com/video/BV1rNVN6HEQV/, https://www.bilibili.com/video/BV1PFmdBmEDA/, https://www.bilibili.com/video/BV1JmG767EBV/, https://www.bilibili.com/video/BV1WdL26LEox/, http://www.bilibili.com/video/av116641530709154, http://www.bilibili.com/video/av115712525931590, http://www.bilibili.com/video/av116628041765144, http://www.bilibili.com/video/av116607036692024",
          "uid": "BV1rNVN6HEQV,BV1PFmdBmEDA,BV1JmG767EBV,BV1WdL26LEox",
          "sample": "弹幕发问号的是不懂音乐吗"
        },
        {
          "source": "Bilibili public search-discovered video comment scan: https://www.bilibili.com/video/BV1rNVN6HEQV/, https://www.bilibili.com/video/BV1PFmdBmEDA/, https://www.bilibili.com/video/BV1JmG767EBV/, https://www.bilibili.com/video/BV1WdL26LEox/, http://www.bilibili.com/video/av116641530709154, http://www.bilibili.com/video/av115712525931590, http://www.bilibili.com/video/av116628041765144, http://www.bilibili.com/video/av116607036692024",
          "uid": "BV1rNVN6HEQV,BV1PFmdBmEDA,BV1JmG767EBV,BV1WdL26LEox",
          "sample": "搞问号的逆天 歌就是好听 你不喜欢可以划走 扣什么问号？"
        },
        {
          "source": "Bilibili public search-discovered video comment scan: https://www.bilibili.com/video/BV1rNVN6HEQV/, https://www.bilibili.com/video/BV1PFmdBmEDA/, https://www.bilibili.com/video/BV1JmG767EBV/, https://www.bilibili.com/video/BV1WdL26LEox/, http://www.bilibili.com/video/av116641530709154, http://www.bilibili.com/video/av115712525931590, http://www.bilibili.com/video/av116628041765144, http://www.bilibili.com/video/av116607036692024",
          "uid": "BV1rNVN6HEQV,BV1PFmdBmEDA,BV1JmG767EBV,BV1WdL26LEox",
          "sample": "打问号的确实只配听跳楼机"
        }
      ]
    },
    {
      "term": "阅读理解满分",
      "evidenceSamples": [
        "就硬夸，阅读理解满分",
        "你是阅读理解满分的人物",
        "阅读理解满分[吃瓜]",
        "阅读理解满分",
        "语文阅读理解满分"
      ],
      "evidenceSources": [
        {
          "source": "Bilibili history-tag harvest: https://www.bilibili.com/video/BV1kRJx6FEwz/ (seed: 范仲淹)",
          "uid": "BV1kRJx6FEwz",
          "sample": "就硬夸，阅读理解满分"
        },
        {
          "source": "Bilibili history-tag harvest: https://www.bilibili.com/video/BV1kRJx6FEwz/ (seed: 范仲淹)",
          "uid": "BV1kRJx6FEwz",
          "sample": "你是阅读理解满分的人物"
        },
        {
          "source": "Bilibili public search-discovered video comment scan: https://www.bilibili.com/video/BV1dM4m1z7iq/, https://www.bilibili.com/video/BV1AijGzNEtS/, https://www.bilibili.com/video/BV1ZYrrYdEB1/, http://www.bilibili.com/video/av918159469, http://www.bilibili.com/video/av1305383041, http://www.bilibili.com/video/av926487480, http://www.bilibili.com/video/av116107025319547, http://www.bilibili.com/video/av116532378078140, http://www.bilibili.com/video/av114568353287913, http://www.bilibili.com/video/av114298105890485, http://www.bilibili.com/video/av113797758977797, http://www.bilibili.com/video/av114708812137755",
          "uid": "BV1dM4m1z7iq,BV1AijGzNEtS,BV1ZYrrYdEB1",
          "sample": "阅读理解满分[吃瓜]"
        },
        {
          "source": "Bilibili public existing evidence-source video comment scan: https://www.bilibili.com/video/BV14aCjYMET7/, https://www.bilibili.com/video/BV1Rt4y1z79i/, https://www.bilibili.com/video/BV1G7G46fEn5/, https://www.bilibili.com/video/BV15YLc6eEWJ/, https://www.bilibili.com/video/BV1uw411Z7jE/, https://www.bilibili.com/video/BV18kpMedEaj/, https://www.bilibili.com/video/BV1vxLg6FEoG/, https://www.bilibili.com/video/BV18gLt6PE79/, https://www.bilibili.com/video/BV1yx4y1q7L9/, https://www.bilibili.com/video/BV1DsCSBhEVv/, https://www.bilibili.com/video/BV1Krg1zEETg/, https://www.bilibili.com/video/BV1w8kUBjE3X/",
          "uid": "BV14aCjYMET7,BV1Rt4y1z79i,BV1G7G46fEn5,BV15YLc6eEWJ,BV1uw411Z7jE,BV18kpMedEaj,BV1vxLg6FEoG,BV18gLt6PE79,BV1yx4y1q7L9,BV1DsCSBhEVv,BV1Krg1zEETg,BV1w8kUBjE3X",
          "sample": "阅读理解满分"
        },
        {
          "source": "Bilibili public existing evidence-source video comment scan: https://www.bilibili.com/video/BV13t411X7HT/, https://www.bilibili.com/video/BV1XCGR6yERU/, https://www.bilibili.com/video/BV1TPQuBAEtM/, https://www.bilibili.com/video/BV162i4BYE8X/, https://www.bilibili.com/video/BV1NkzuYCEd2/, https://www.bilibili.com/video/BV1C3hwzrERT/",
          "uid": "BV13t411X7HT,BV1XCGR6yERU,BV1TPQuBAEtM,BV162i4BYE8X,BV1NkzuYCEd2,BV1C3hwzrERT",
          "sample": "语文阅读理解满分"
        },
        {
          "source": "Bilibili public existing evidence-source video comment scan: https://www.bilibili.com/video/BV13t411X7HT/, https://www.bilibili.com/video/BV1XCGR6yERU/, https://www.bilibili.com/video/BV1TPQuBAEtM/, https://www.bilibili.com/video/BV162i4BYE8X/, https://www.bilibili.com/video/BV1NkzuYCEd2/, https://www.bilibili.com/video/BV1C3hwzrERT/",
          "uid": "BV13t411X7HT,BV1XCGR6yERU,BV1TPQuBAEtM,BV162i4BYE8X,BV1NkzuYCEd2,BV1C3hwzrERT",
          "sample": "阅读理解满分"
        },
        {
          "source": "Bilibili public search-discovered video comment scan: https://www.bilibili.com/video/BV13t411X7HT/, https://www.bilibili.com/video/BV1CuVa6YErA/, https://www.bilibili.com/video/BV1BV4y1b7d8/, https://www.bilibili.com/video/BV1q66iBAELQ/, https://www.bilibili.com/video/BV1fPR9BDEMU/, https://www.bilibili.com/video/BV18S4y177ND/, https://www.bilibili.com/video/BV15e4y147ri/, https://www.bilibili.com/video/BV1awL56AEJX/, https://www.bilibili.com/video/BV1pt411Z7XJ/, https://www.bilibili.com/video/BV1ct421A7Nd/, https://www.bilibili.com/video/BV1ve4y1r7op/, https://www.bilibili.com/video/BV1pVVu6aEBH/, http://www.bilibili.com/video/av37062694, http://www.bilibili.com/video/av115984333605739, http://www.bilibili.com/video/av646977392, http://www.bilibili.com/video/av1753596063, http://www.bilibili.com/video/av286123969, http://www.bilibili.com/video/av115682578532560, http://www.bilibili.com/video/av1152477971, http://www.bilibili.com/video/av116137157202027, http://www.bilibili.com/video/av800239179, http://www.bilibili.com/video/av1454063932, http://www.bilibili.com/video/av598416819, http://www.bilibili.com/video/av115676186413163, http://www.bilibili.com/video/av9816251, http://www.bilibili.com/video/av555976082, http://www.bilibili.com/video/av1756199414, http://www.bilibili.com/video/av510561306, http://www.bilibili.com/video/av684804996, http://www.bilibili.com/video/av112968897464267, http://www.bilibili.com/video/av771057939, http://www.bilibili.com/video/av113851160856881, http://www.bilibili.com/video/av1305446528, http://www.bilibili.com/video/av112924102296299, http://www.bilibili.com/video/av116618579411550, http://www.bilibili.com/video/av810639525, http://www.bilibili.com/video/av344984988, http://www.bilibili.com/video/av801894462, http://www.bilibili.com/video/av113734676710538, http://www.bilibili.com/video/av116080299214935, http://www.bilibili.com/video/av264120589, http://www.bilibili.com/video/av589141976, http://www.bilibili.com/video/av1204066164, http://www.bilibili.com/video/av114805901890987, http://www.bilibili.com/video/av113708772624300, http://www.bilibili.com/video/av114303810145249, http://www.bilibili.com/video/av521138563, http://www.bilibili.com/video/av204433003, http://www.bilibili.com/video/av116658777623152, http://www.bilibili.com/video/av116544675776496, http://www.bilibili.com/video/av116585025114286, http://www.bilibili.com/video/av558586079, http://www.bilibili.com/video/av116645406251151, http://www.bilibili.com/video/av116663542353840, http://www.bilibili.com/video/av116619502164179, http://www.bilibili.com/video/av114488527297820, http://www.bilibili.com/video/av116663223585765, http://www.bilibili.com/video/av114992078659331, http://www.bilibili.com/video/av1805782732, http://www.bilibili.com/video/av115479138012747, http://www.bilibili.com/video/av116429785401338, http://www.bilibili.com/video/av1350384655, http://www.bilibili.com/video/av116385141228607, http://www.bilibili.com/video/av116639567708855, http://www.bilibili.com/video/av116553936798038, http://www.bilibili.com/video/av116619116286309, http://www.bilibili.com/video/av116465168554829, http://www.bilibili.com/video/av114209958467882, http://www.bilibili.com/video/av114721294389478, http://www.bilibili.com/video/av115904088117402, http://www.bilibili.com/video/av116255570790001, http://www.bilibili.com/video/av116607640671890, http://www.bilibili.com/video/av115835066646811, http://www.bilibili.com/video/av116663206872887, http://www.bilibili.com/video/av326389047, http://www.bilibili.com/video/av114873681973965, http://www.bilibili.com/video/av116664012243644, http://www.bilibili.com/video/av116662384725876, http://www.bilibili.com/video/av115139902709640, http://www.bilibili.com/video/av923733631, http://www.bilibili.com/video/av114792866059629, http://www.bilibili.com/video/av116651026551962, http://www.bilibili.com/video/av116662183397097, http://www.bilibili.com/video/av116650942663426, http://www.bilibili.com/video/av116613395253133, http://www.bilibili.com/video/av115477594639550, http://www.bilibili.com/video/av116657267805991, http://www.bilibili.com/video/av116509628171816, http://www.bilibili.com/video/av116663978563580, http://www.bilibili.com/video/av116443442059456, http://www.bilibili.com/video/av116635155300869, http://www.bilibili.com/video/av113575880362447, http://www.bilibili.com/video/av114331324912237, http://www.bilibili.com/video/av870953158, http://www.bilibili.com/video/av728513972, http://www.bilibili.com/video/av33911794, http://www.bilibili.com/video/av116660354683212, http://www.bilibili.com/video/av40702784, http://www.bilibili.com/video/av1853096718, http://www.bilibili.com/video/av608527755, http://www.bilibili.com/video/av115784986656783, http://www.bilibili.com/video/av113238423442538, http://www.bilibili.com/video/av1254248262, http://www.bilibili.com/video/av116539273578167, http://www.bilibili.com/video/av116414165877273",
          "uid": "BV13t411X7HT,BV1CuVa6YErA,BV1BV4y1b7d8,BV1q66iBAELQ,BV1fPR9BDEMU,BV18S4y177ND,BV15e4y147ri,BV1awL56AEJX,BV1pt411Z7XJ,BV1ct421A7Nd,BV1ve4y1r7op,BV1pVVu6aEBH",
          "sample": "阅读理解满分"
        },
        {
          "source": "Bilibili public search-discovered video comment scan: https://www.bilibili.com/video/BV13t411X7HT/, https://www.bilibili.com/video/BV1CuVa6YErA/, https://www.bilibili.com/video/BV1BV4y1b7d8/, https://www.bilibili.com/video/BV1q66iBAELQ/, https://www.bilibili.com/video/BV1fPR9BDEMU/, https://www.bilibili.com/video/BV18S4y177ND/, https://www.bilibili.com/video/BV15e4y147ri/, https://www.bilibili.com/video/BV1awL56AEJX/, https://www.bilibili.com/video/BV1pt411Z7XJ/, https://www.bilibili.com/video/BV1ct421A7Nd/, https://www.bilibili.com/video/BV1ve4y1r7op/, https://www.bilibili.com/video/BV1pVVu6aEBH/, http://www.bilibili.com/video/av37062694, http://www.bilibili.com/video/av115984333605739, http://www.bilibili.com/video/av646977392, http://www.bilibili.com/video/av1753596063, http://www.bilibili.com/video/av286123969, http://www.bilibili.com/video/av115682578532560, http://www.bilibili.com/video/av1152477971, http://www.bilibili.com/video/av116137157202027, http://www.bilibili.com/video/av800239179, http://www.bilibili.com/video/av1454063932, http://www.bilibili.com/video/av598416819, http://www.bilibili.com/video/av115676186413163, http://www.bilibili.com/video/av9816251, http://www.bilibili.com/video/av555976082, http://www.bilibili.com/video/av1756199414, http://www.bilibili.com/video/av510561306, http://www.bilibili.com/video/av684804996, http://www.bilibili.com/video/av112968897464267, http://www.bilibili.com/video/av771057939, http://www.bilibili.com/video/av113851160856881, http://www.bilibili.com/video/av1305446528, http://www.bilibili.com/video/av112924102296299, http://www.bilibili.com/video/av116618579411550, http://www.bilibili.com/video/av810639525, http://www.bilibili.com/video/av344984988, http://www.bilibili.com/video/av801894462, http://www.bilibili.com/video/av113734676710538, http://www.bilibili.com/video/av116080299214935, http://www.bilibili.com/video/av264120589, http://www.bilibili.com/video/av589141976, http://www.bilibili.com/video/av1204066164, http://www.bilibili.com/video/av114805901890987, http://www.bilibili.com/video/av113708772624300, http://www.bilibili.com/video/av114303810145249, http://www.bilibili.com/video/av521138563, http://www.bilibili.com/video/av204433003, http://www.bilibili.com/video/av116658777623152, http://www.bilibili.com/video/av116544675776496, http://www.bilibili.com/video/av116585025114286, http://www.bilibili.com/video/av558586079, http://www.bilibili.com/video/av116645406251151, http://www.bilibili.com/video/av116663542353840, http://www.bilibili.com/video/av116619502164179, http://www.bilibili.com/video/av114488527297820, http://www.bilibili.com/video/av116663223585765, http://www.bilibili.com/video/av114992078659331, http://www.bilibili.com/video/av1805782732, http://www.bilibili.com/video/av115479138012747, http://www.bilibili.com/video/av116429785401338, http://www.bilibili.com/video/av1350384655, http://www.bilibili.com/video/av116385141228607, http://www.bilibili.com/video/av116639567708855, http://www.bilibili.com/video/av116553936798038, http://www.bilibili.com/video/av116619116286309, http://www.bilibili.com/video/av116465168554829, http://www.bilibili.com/video/av114209958467882, http://www.bilibili.com/video/av114721294389478, http://www.bilibili.com/video/av115904088117402, http://www.bilibili.com/video/av116255570790001, http://www.bilibili.com/video/av116607640671890, http://www.bilibili.com/video/av115835066646811, http://www.bilibili.com/video/av116663206872887, http://www.bilibili.com/video/av326389047, http://www.bilibili.com/video/av114873681973965, http://www.bilibili.com/video/av116664012243644, http://www.bilibili.com/video/av116662384725876, http://www.bilibili.com/video/av115139902709640, http://www.bilibili.com/video/av923733631, http://www.bilibili.com/video/av114792866059629, http://www.bilibili.com/video/av116651026551962, http://www.bilibili.com/video/av116662183397097, http://www.bilibili.com/video/av116650942663426, http://www.bilibili.com/video/av116613395253133, http://www.bilibili.com/video/av115477594639550, http://www.bilibili.com/video/av116657267805991, http://www.bilibili.com/video/av116509628171816, http://www.bilibili.com/video/av116663978563580, http://www.bilibili.com/video/av116443442059456, http://www.bilibili.com/video/av116635155300869, http://www.bilibili.com/video/av113575880362447, http://www.bilibili.com/video/av114331324912237, http://www.bilibili.com/video/av870953158, http://www.bilibili.com/video/av728513972, http://www.bilibili.com/video/av33911794, http://www.bilibili.com/video/av116660354683212, http://www.bilibili.com/video/av40702784, http://www.bilibili.com/video/av1853096718, http://www.bilibili.com/video/av608527755, http://www.bilibili.com/video/av115784986656783, http://www.bilibili.com/video/av113238423442538, http://www.bilibili.com/video/av1254248262, http://www.bilibili.com/video/av116539273578167, http://www.bilibili.com/video/av116414165877273",
          "uid": "BV13t411X7HT,BV1CuVa6YErA,BV1BV4y1b7d8,BV1q66iBAELQ,BV1fPR9BDEMU,BV18S4y177ND,BV15e4y147ri,BV1awL56AEJX,BV1pt411Z7XJ,BV1ct421A7Nd,BV1ve4y1r7op,BV1pVVu6aEBH",
          "sample": "语文阅读理解满分"
        }
      ]
    },
    {
      "term": "队迷",
      "evidenceSamples": [
        "up怎么看待队迷，你不觉得土生土长的中国人是美国某只非常年强队的队迷是种很搞笑的说法吗[doge]",
        "我从阿根廷队迷到梅西人迷到巴萨队迷，梅西走的前后对巴萨失望极了，就看看欧冠，看看梅西，看看阿根廷世界杯，因为弗里克又开始看巴萨，现在快成教练迷了，一个牛逼的教练对球队影响太大了，从2022世界杯决赛，到最近的欧冠决赛，名帅真的太迷人了",
        "刚从虎扑车区出来我觉得太对了 现在车区为了黑马雷斯卡已经快进到老谢替老马说话不如王楚淇爱车了[笑哭]这种纯队迷真的和客观边都不沾",
        "我随着年龄的增长慢慢从队迷转变成人迷了，不知道其他年纪比较大的球迷是不是这样。"
      ],
      "evidenceSources": [
        {
          "source": "Bilibili public search-discovered video comment scan: https://www.bilibili.com/video/BV1wDSLBMEU4/, https://www.bilibili.com/video/BV1roeXz9E3D/, https://www.bilibili.com/video/BV1trGW61EED/, https://www.bilibili.com/video/BV1UeawzSErm/, https://www.bilibili.com/video/BV1gSLt6qEMu/, https://www.bilibili.com/video/BV1jwGs6wExs/, http://www.bilibili.com/video/av115624999129571, http://www.bilibili.com/video/av115133745535921, http://www.bilibili.com/video/av1105681755, http://www.bilibili.com/video/av114636586225553, http://www.bilibili.com/video/av1355627373, http://www.bilibili.com/video/av115027528914096, http://www.bilibili.com/video/av114583234682722, http://www.bilibili.com/video/av114713425875055, http://www.bilibili.com/video/av114573738843794, http://www.bilibili.com/video/av524720766, http://www.bilibili.com/video/av114651350241934, http://www.bilibili.com/video/av115653000366524, http://www.bilibili.com/video/av115104318292004, http://www.bilibili.com/video/av116612472511450, http://www.bilibili.com/video/av115376696467317, http://www.bilibili.com/video/av115254960916939, http://www.bilibili.com/video/av116622538900129, http://www.bilibili.com/video/av417763577, http://www.bilibili.com/video/av116634115248102, http://www.bilibili.com/video/av116630659013398, http://www.bilibili.com/video/av116630071871122, http://www.bilibili.com/video/av116628377312058, http://www.bilibili.com/video/av116625978170274, http://www.bilibili.com/video/av116624619214054, http://www.bilibili.com/video/av116623629424224, http://www.bilibili.com/video/av116623025441531, http://www.bilibili.com/video/av116470252115967, http://www.bilibili.com/video/av116420859925535, http://www.bilibili.com/video/av115676152861028, http://www.bilibili.com/video/av116481224415464, http://www.bilibili.com/video/av116441395238820, http://www.bilibili.com/video/av116612992599096, http://www.bilibili.com/video/av116526589943508, http://www.bilibili.com/video/av116526841594544, http://www.bilibili.com/video/av870861549, http://www.bilibili.com/video/av116632823272586, http://www.bilibili.com/video/av116632538058537, http://www.bilibili.com/video/av116630256555206, http://www.bilibili.com/video/av116629853700676, http://www.bilibili.com/video/av116627471472838, http://www.bilibili.com/video/av116627169548371",
          "uid": "BV1wDSLBMEU4,BV1roeXz9E3D,BV1trGW61EED,BV1UeawzSErm,BV1gSLt6qEMu,BV1jwGs6wExs",
          "sample": "up怎么看待队迷，你不觉得土生土长的中国人是美国某只非常年强队的队迷是种很搞笑的说法吗[doge]"
        },
        {
          "source": "Bilibili public search-discovered video comment scan: https://www.bilibili.com/video/BV1wDSLBMEU4/, https://www.bilibili.com/video/BV1roeXz9E3D/, https://www.bilibili.com/video/BV1UdGR6iEvh/, https://www.bilibili.com/video/BV1UeawzSErm/, https://www.bilibili.com/video/BV1gSLt6qEMu/, https://www.bilibili.com/video/BV1e64ezMEtb/, http://www.bilibili.com/video/av115624999129571, http://www.bilibili.com/video/av115133745535921, http://www.bilibili.com/video/av1105681755, http://www.bilibili.com/video/av114636586225553, http://www.bilibili.com/video/av1355627373, http://www.bilibili.com/video/av115027528914096, http://www.bilibili.com/video/av114761324894492, http://www.bilibili.com/video/av114583234682722, http://www.bilibili.com/video/av114713425875055, http://www.bilibili.com/video/av114573738843794, http://www.bilibili.com/video/av524720766, http://www.bilibili.com/video/av114651350241934, http://www.bilibili.com/video/av115653000366524, http://www.bilibili.com/video/av115104318292004, http://www.bilibili.com/video/av116612472511450, http://www.bilibili.com/video/av115376696467317, http://www.bilibili.com/video/av115254960916939, http://www.bilibili.com/video/av116622538900129, http://www.bilibili.com/video/av417763577, http://www.bilibili.com/video/av116634115248102, http://www.bilibili.com/video/av116630659013398, http://www.bilibili.com/video/av116630071871122, http://www.bilibili.com/video/av116628377312058, http://www.bilibili.com/video/av116625978170274, http://www.bilibili.com/video/av116623629424224, http://www.bilibili.com/video/av116623025441531, http://www.bilibili.com/video/av116470252115967, http://www.bilibili.com/video/av116420859925535, http://www.bilibili.com/video/av115676152861028, http://www.bilibili.com/video/av116481224415464, http://www.bilibili.com/video/av116441395238820, http://www.bilibili.com/video/av116612992599096, http://www.bilibili.com/video/av116526589943508, http://www.bilibili.com/video/av116526841594544, http://www.bilibili.com/video/av870861549, http://www.bilibili.com/video/av116634450663997, http://www.bilibili.com/video/av394478362, http://www.bilibili.com/video/av116623461581929",
          "uid": "BV1wDSLBMEU4,BV1roeXz9E3D,BV1UdGR6iEvh,BV1UeawzSErm,BV1gSLt6qEMu,BV1e64ezMEtb",
          "sample": "up怎么看待队迷，你不觉得土生土长的中国人是美国某只非常年强队的队迷是种很搞笑的说法吗[doge]"
        },
        {
          "source": "Bilibili public search-discovered video comment scan: https://www.bilibili.com/video/BV1wDSLBMEU4/, https://www.bilibili.com/video/BV1roeXz9E3D/, https://www.bilibili.com/video/BV1sufoBSEeD/, https://www.bilibili.com/video/BV1UeawzSErm/, https://www.bilibili.com/video/BV1gSLt6qEMu/, https://www.bilibili.com/video/BV19315B3Etd/, http://www.bilibili.com/video/av115624999129571, http://www.bilibili.com/video/av115133745535921, http://www.bilibili.com/video/av1105681755, http://www.bilibili.com/video/av114636586225553, http://www.bilibili.com/video/av1355627373, http://www.bilibili.com/video/av115027528914096, http://www.bilibili.com/video/av114583234682722, http://www.bilibili.com/video/av114713425875055, http://www.bilibili.com/video/av114573738843794, http://www.bilibili.com/video/av524720766, http://www.bilibili.com/video/av114651350241934, http://www.bilibili.com/video/av115653000366524, http://www.bilibili.com/video/av115104318292004, http://www.bilibili.com/video/av116612472511450, http://www.bilibili.com/video/av115376696467317, http://www.bilibili.com/video/av115254960916939, http://www.bilibili.com/video/av116622538900129, http://www.bilibili.com/video/av417763577, http://www.bilibili.com/video/av116634115248102, http://www.bilibili.com/video/av116630659013398, http://www.bilibili.com/video/av116630071871122, http://www.bilibili.com/video/av116628377312058, http://www.bilibili.com/video/av116625978170274, http://www.bilibili.com/video/av116624619214054, http://www.bilibili.com/video/av116630256355038, http://www.bilibili.com/video/av116623629424224, http://www.bilibili.com/video/av116623025441531, http://www.bilibili.com/video/av115676152861028, http://www.bilibili.com/video/av115626123265986, http://www.bilibili.com/video/av116481224415464, http://www.bilibili.com/video/av116441395238820, http://www.bilibili.com/video/av116612992599096, http://www.bilibili.com/video/av116526589943508, http://www.bilibili.com/video/av116526841594544, http://www.bilibili.com/video/av870861549, http://www.bilibili.com/video/av116012217339104, http://www.bilibili.com/video/av115473350006167, http://www.bilibili.com/video/av113786769904887, http://www.bilibili.com/video/av757995984, http://www.bilibili.com/video/av908601719",
          "uid": "BV1wDSLBMEU4,BV1roeXz9E3D,BV1sufoBSEeD,BV1UeawzSErm,BV1gSLt6qEMu,BV19315B3Etd",
          "sample": "up怎么看待队迷，你不觉得土生土长的中国人是美国某只非常年强队的队迷是种很搞笑的说法吗[doge]"
        },
        {
          "source": "Bilibili public search-discovered video comment scan: https://www.bilibili.com/video/BV11pg2zJENc/, https://www.bilibili.com/video/BV1nKVN6QEZB/, https://www.bilibili.com/video/BV1hv4y1d7Sv/, https://www.bilibili.com/video/BV1SYRZB7EKq/, http://www.bilibili.com/video/av114775249915024",
          "uid": "BV11pg2zJENc,BV1nKVN6QEZB,BV1hv4y1d7Sv,BV1SYRZB7EKq",
          "sample": "我从阿根廷队迷到梅西人迷到巴萨队迷，梅西走的前后对巴萨失望极了，就看看欧冠，看看梅西，看看阿根廷世界杯，因为弗里克又开始看巴萨，现在快成教练迷了，一个牛逼的教练对球队影响太大了，从2022世界杯决赛，到最近的欧冠决赛，名帅真的太迷人了"
        },
        {
          "source": "Bilibili public search-discovered video comment scan: https://www.bilibili.com/video/BV11pg2zJENc/, https://www.bilibili.com/video/BV1ETVA6GEhQ/, https://www.bilibili.com/video/BV1FaRiBzE6q/, https://www.bilibili.com/video/BV1hv4y1d7Sv/, http://www.bilibili.com/video/av114775249915024",
          "uid": "BV11pg2zJENc,BV1ETVA6GEhQ,BV1FaRiBzE6q,BV1hv4y1d7Sv",
          "sample": "我从阿根廷队迷到梅西人迷到巴萨队迷，梅西走的前后对巴萨失望极了，就看看欧冠，看看梅西，看看阿根廷世界杯，因为弗里克又开始看巴萨，现在快成教练迷了，一个牛逼的教练对球队影响太大了，从2022世界杯决赛，到最近的欧冠决赛，名帅真的太迷人了"
        },
        {
          "source": "Bilibili public search-discovered video comment scan: https://www.bilibili.com/video/BV1Nz1FBdEi6/, https://www.bilibili.com/video/BV11pg2zJENc/, https://www.bilibili.com/video/BV1SYRZB7EKq/, https://www.bilibili.com/video/BV1t772zuEtW/, http://www.bilibili.com/video/av115480077599938, http://www.bilibili.com/video/av114775249915024",
          "uid": "BV1Nz1FBdEi6,BV11pg2zJENc,BV1SYRZB7EKq,BV1t772zuEtW",
          "sample": "我从阿根廷队迷到梅西人迷到巴萨队迷，梅西走的前后对巴萨失望极了，就看看欧冠，看看梅西，看看阿根廷世界杯，因为弗里克又开始看巴萨，现在快成教练迷了，一个牛逼的教练对球队影响太大了，从2022世界杯决赛，到最近的欧冠决赛，名帅真的太迷人了"
        },
        {
          "source": "Bilibili public search-discovered video comment scan: https://www.bilibili.com/video/BV1nBi1BDEE4/, https://www.bilibili.com/video/BV1VAVK6kEgR/, https://www.bilibili.com/video/BV1CpQPByEC4/, https://www.bilibili.com/video/BV1GGGf6pE1r/, http://www.bilibili.com/video/av115854024905837",
          "uid": "BV1nBi1BDEE4,BV1VAVK6kEgR,BV1CpQPByEC4,BV1GGGf6pE1r",
          "sample": "刚从虎扑车区出来我觉得太对了 现在车区为了黑马雷斯卡已经快进到老谢替老马说话不如王楚淇爱车了[笑哭]这种纯队迷真的和客观边都不沾"
        },
        {
          "source": "Bilibili public search-discovered video comment scan: https://www.bilibili.com/video/BV1nBi1BDEE4/, https://www.bilibili.com/video/BV1VAVK6kEgR/, https://www.bilibili.com/video/BV1CpQPByEC4/, https://www.bilibili.com/video/BV1GGGf6pE1r/, http://www.bilibili.com/video/av115854024905837",
          "uid": "BV1nBi1BDEE4,BV1VAVK6kEgR,BV1CpQPByEC4,BV1GGGf6pE1r",
          "sample": "我随着年龄的增长慢慢从队迷转变成人迷了，不知道其他年纪比较大的球迷是不是这样。"
        }
      ]
    },
    {
      "term": "阮阮",
      "evidenceSamples": [
        "我感觉小砍是最惨的，因为阮阮是她带进来的，阮阮违约了他应该是最难受的",
        "最近风声这么大 team和老谢都在一个平台 老谢本人不大可能不知道这个事吧[笑哭]但是也不否认他和阮阮可能是同一个人的可能性",
        "我感觉可能是阮阮没走正常的离职手续就偷跑了，然后现在大概是失联状态。。因此mhn说“回我们知道的东西”和“不能胡说八道”，因为mhn也没有其他的信息，他不能肯定rr怎么怎么样了，只能展示先履行合同（？）"
      ],
      "evidenceSources": [
        {
          "source": "Bilibili public search-discovered video comment scan: https://www.bilibili.com/video/BV1ZUc4ztEQJ/, https://www.bilibili.com/video/BV18L75znEJU/, https://www.bilibili.com/video/BV1MGQmB3EHS/, http://www.bilibili.com/video/av116051593461812",
          "uid": "BV1ZUc4ztEQJ,BV18L75znEJU,BV1MGQmB3EHS",
          "sample": "我感觉小砍是最惨的，因为阮阮是她带进来的，阮阮违约了他应该是最难受的"
        },
        {
          "source": "Bilibili public search-discovered video comment scan: https://www.bilibili.com/video/BV1ZUc4ztEQJ/, https://www.bilibili.com/video/BV18L75znEJU/, https://www.bilibili.com/video/BV1MGQmB3EHS/, http://www.bilibili.com/video/av116051593461812",
          "uid": "BV1ZUc4ztEQJ,BV18L75znEJU,BV1MGQmB3EHS",
          "sample": "最近风声这么大 team和老谢都在一个平台 老谢本人不大可能不知道这个事吧[笑哭]但是也不否认他和阮阮可能是同一个人的可能性"
        },
        {
          "source": "Bilibili public search-discovered video comment scan: https://www.bilibili.com/video/BV1P9jRzXEgr/, http://www.bilibili.com/video/av116561402663107, http://www.bilibili.com/video/av116589001179480, http://www.bilibili.com/video/av114579896016783, http://www.bilibili.com/video/av116578649637201, http://www.bilibili.com/video/av115129131736009, http://www.bilibili.com/video/av114569410256080",
          "uid": "BV1P9jRzXEgr",
          "sample": "我感觉可能是阮阮没走正常的离职手续就偷跑了，然后现在大概是失联状态。。因此mhn说“回我们知道的东西”和“不能胡说八道”，因为mhn也没有其他的信息，他不能肯定rr怎么怎么样了，只能展示先履行合同（？）"
        }
      ]
    }
  ]
}
